{
  "metadata": {
    "driver": "RODRIGO",
    "data": "23/12/2025",
    "total_entregas": 32,
    "total_itens": 39,
    "gerado_em": "2025-12-30T00:00:00Z",
    "fonte": "export WhatsApp validado manualmente"
  },
  "items": [
    {
      "id_sale_delivery": "001",
      "produto": "prensado",
      "quantidade": 5,
      "endereco_1": "Rua do Dólar 592",
      "driver": "RODRIGO",
      "data_entrega": "23/12/2025"
    },
    {
      "id_sale_delivery": "002",
      "produto": "prensado",
      "quantidade": 1,
      "endereco_1": "Av Getúlio Vargas 2380",
      "driver": "RODRIGO",
      "data_entrega": "23/12/2025"
    },
    {
      "id_sale_delivery": "003",
      "produto": "orange",
      "quantidade": 15,
      "endereco_1": "Senador Furtado 515",
      "driver": "RODRIGO",
      "data_entrega": "23/12/2025"
    },
    {
      "id_sale_delivery": "004",
      "produto": "exporta",
      "quantidade": 2,
      "endereco_1": "Rua Professor Eudóxio Cassassanta Pereira 551",
      "driver": "RODRIGO",
      "data_entrega": "23/12/2025"
    },
    {
      "id_sale_delivery": "005",
      "produto": "colombia gold",
      "quantidade": 10,
      "endereco_1": "Rua Santa Catarina 580",
      "driver": "RODRIGO",
      "data_entrega": "23/12/2025"
    },
    {
      "id_sale_delivery": "006",
      "produto": "escama",
      "quantidade": 1,
      "endereco_1": "Rua Hercio Martins Gomide 25, Jardim Patrícia",
      "driver": "RODRIGO",
      "data_entrega": "23/12/2025"
    },
    {
      "id_sale_delivery": "007",
      "produto": "prensado",
      "quantidade": 1,
      "endereco_1": "Rua Dolorita Elias do Nascimento, 220",
      "driver": "RODRIGO",
      "data_entrega": "23/12/2025"
    },
    {
      "id_sale_delivery": "008",
      "produto": "manga rosa",
      "quantidade": 5,
      "endereco_1": "Av Vereador Carlito Cordeiro 2315",
      "driver": "RODRIGO",
      "data_entrega": "23/12/2025"
    },
    {
      "id_sale_delivery": "009",
      "produto": "manga rosa",
      "quantidade": 5,
      "endereco_1": "Francisco Antônio de Oliveira, 1770",
      "driver": "RODRIGO",
      "data_entrega": "23/12/2025"
    },
    {
      "id_sale_delivery": "010",
      "produto": "escama",
      "quantidade": 1,
      "endereco_1": "Rua do Ensino 98, Santa Mônica",
      "driver": "RODRIGO",
      "data_entrega": "23/12/2025"
    },
    {
      "id_sale_delivery": "011",
      "produto": "prensado",
      "quantidade": 2,
      "endereco_1": "Rua do Carteiro, 760 (casa na esquina)",
      "driver": "RODRIGO",
      "data_entrega": "23/12/2025"
    },
    {
      "id_sale_delivery": "012",
      "produto": "prensado",
      "quantidade": 1,
      "endereco_1": "Cleanto Vieira Gonçalves 1645",
      "driver": "RODRIGO",
      "data_entrega": "23/12/2025"
    },
    {
      "id_sale_delivery": "013",
      "produto": "prensado",
      "quantidade": 1,
      "endereco_1": "Antônio Scanapieco 166",
      "driver": "RODRIGO",
      "data_entrega": "23/12/2025"
    },
    {
      "id_sale_delivery": "014",
      "produto": "elon musk",
      "quantidade": 5,
      "endereco_1": "Rua Sebastião Rangel 842",
      "driver": "RODRIGO",
      "data_entrega": "23/12/2025"
    },
    {
      "id_sale_delivery": "014",
      "produto": "md",
      "quantidade": 1,
      "endereco_1": "Rua Sebastião Rangel 842",
      "driver": "RODRIGO",
      "data_entrega": "23/12/2025"
    },
    {
      "id_sale_delivery": "015",
      "produto": "exporta",
      "quantidade": 1,
      "endereco_1": "Risde Atiie 60, Jardim Europa",
      "driver": "RODRIGO",
      "data_entrega": "23/12/2025"
    },
    {
      "id_sale_delivery": "016",
      "produto": "pretinho uva",
      "quantidade": 5,
      "endereco_1": "Rua das Gaivotas 657",
      "driver": "RODRIGO",
      "data_entrega": "23/12/2025"
    },
    {
      "id_sale_delivery": "017",
      "produto": "prensado",
      "quantidade": 1,
      "endereco_1": "Rua José Carrijo, 1289",
      "driver": "RODRIGO",
      "data_entrega": "23/12/2025"
    },
    {
      "id_sale_delivery": "018",
      "produto": "prensado",
      "quantidade": 1,
      "endereco_1": "Rua Alípio José de Souza 172, Laranjeiras",
      "driver": "RODRIGO",
      "data_entrega": "23/12/2025"
    },
    {
      "id_sale_delivery": "019",
      "produto": "sower",
      "quantidade": 6,
      "endereco_1": "Rua SU1 100, Cond. Spazio Único",
      "driver": "RODRIGO",
      "data_entrega": "23/12/2025"
    },
    {
      "id_sale_delivery": "019",
      "produto": "dry",
      "quantidade": 3,
      "endereco_1": "Rua SU1 100, Cond. Spazio Único",
      "driver": "RODRIGO",
      "data_entrega": "23/12/2025"
    },
    {
      "id_sale_delivery": "019",
      "produto": "tabaco",
      "quantidade": 1,
      "endereco_1": "Rua SU1 100, Cond. Spazio Único",
      "driver": "RODRIGO",
      "data_entrega": "23/12/2025"
    },
    {
      "id_sale_delivery": "019",
      "produto": "seda",
      "quantidade": 1,
      "endereco_1": "Rua SU1 100, Cond. Spazio Único",
      "driver": "RODRIGO",
      "data_entrega": "23/12/2025"
    },
    {
      "id_sale_delivery": "020",
      "produto": "prensado",
      "quantidade": 1,
      "endereco_1": "Rua do Estudante 236",
      "driver": "RODRIGO",
      "data_entrega": "23/12/2025"
    },
    {
      "id_sale_delivery": "021",
      "produto": "prensado",
      "quantidade": 1,
      "endereco_1": "Osmar Teixeira Moraes 101",
      "driver": "RODRIGO",
      "data_entrega": "23/12/2025"
    },
    {
      "id_sale_delivery": "022",
      "produto": "prensado",
      "quantidade": 1,
      "endereco_1": "Rua Bolonha 105, Jardim Europa",
      "driver": "RODRIGO",
      "data_entrega": "23/12/2025"
    },
    {
      "id_sale_delivery": "023",
      "produto": "manga rosa",
      "quantidade": 5,
      "endereco_1": "Av dos Jardins 250",
      "driver": "RODRIGO",
      "data_entrega": "23/12/2025"
    },
    {
      "id_sale_delivery": "023",
      "produto": "super lemon",
      "quantidade": 1,
      "endereco_1": "Av dos Jardins 250",
      "driver": "RODRIGO",
      "data_entrega": "23/12/2025"
    },
    {
      "id_sale_delivery": "024",
      "produto": "manga rosa",
      "quantidade": 10,
      "endereco_1": "Gabão 40",
      "driver": "RODRIGO",
      "data_entrega": "23/12/2025"
    },
    {
      "id_sale_delivery": "025",
      "produto": "colombia gold",
      "quantidade": 5,
      "endereco_1": "Rua Professor Euler Lannes Bernardes 841",
      "driver": "RODRIGO",
      "data_entrega": "23/12/2025"
    },
    {
      "id_sale_delivery": "026",
      "produto": "orange",
      "quantidade": 4,
      "endereco_1": "Maria Esperança 09",
      "driver": "RODRIGO",
      "data_entrega": "23/12/2025"
    },
    {
      "id_sale_delivery": "027",
      "produto": "colombia gold",
      "quantidade": 10,
      "endereco_1": "Rua Imperatriz Leopoldina 100, Tubalina",
      "driver": "RODRIGO",
      "data_entrega": "23/12/2025"
    },
    {
      "id_sale_delivery": "028",
      "produto": "colombia gold",
      "quantidade": 5,
      "endereco_1": "Av Dr Munir Tannus Abidalla 201",
      "driver": "RODRIGO",
      "data_entrega": "23/12/2025"
    },
    {
      "id_sale_delivery": "029",
      "produto": "manga rosa",
      "quantidade": 5,
      "endereco_1": "Rua Orozimbro Ribeiro 1428, Santa Mônica",
      "driver": "RODRIGO",
      "data_entrega": "23/12/2025"
    },
    {
      "id_sale_delivery": "029",
      "produto": "arizona",
      "quantidade": 5,
      "endereco_1": "Rua Orozimbro Ribeiro 1428, Santa Mônica",
      "driver": "RODRIGO",
      "data_entrega": "23/12/2025"
    },
    {
      "id_sale_delivery": "030",
      "produto": "arizona",
      "quantidade": 15,
      "endereco_1": "Rua Quintino Bocaiúva 2557",
      "driver": "RODRIGO",
      "data_entrega": "23/12/2025"
    },
    {
      "id_sale_delivery": "031",
      "produto": "exporta",
      "quantidade": 1,
      "endereco_1": "Paris 80",
      "driver": "RODRIGO",
      "data_entrega": "23/12/2025"
    },
    {
      "id_sale_delivery": "032",
      "produto": "marmita comercial",
      "quantidade": 1,
      "endereco_1": "Rua Antônio Rezende Chaves 1424",
      "driver": "RODRIGO",
      "data_entrega": "23/12/2025"
    }
  ]
}
